{"stats":{"minecraft:picked_up":{"minecraft:crafting_table":1,"born_in_chaos_v1:corpse_maggot":2,"minecraft:stick":5,"minecraft:raw_iron":16,"minecraft:cooked_porkchop":4,"minecraft:spruce_log":9,"alexsmobs:animal_dictionary":1,"minecraft:dirt":1,"ars_nouveau:worn_notebook":1,"minecraft:granite":2,"minecraft:coal":35,"minecraft:cobblestone":43},"minecraft:mined":{"minecraft:iron_ore":16,"minecraft:crafting_table":1,"minecraft:granite":2,"minecraft:coal_ore":36,"minecraft:dirt":1,"minecraft:spruce_leaves":3,"minecraft:stone":42},"minecraft:killed_by":{"minecraft:skeleton":1,"born_in_chaos_v1:zombie_lumberjack":1},"minecraft:custom":{"minecraft:time_since_rest":3751,"minecraft:sprint_one_cm":24258,"minecraft:damage_taken":715,"minecraft:walk_one_cm":13222,"minecraft:mob_kills":1,"minecraft:damage_dealt":449,"minecraft:interact_with_crafting_table":2,"minecraft:fly_one_cm":3323,"minecraft:crouch_one_cm":87,"minecraft:play_time":25899,"minecraft:deaths":2,"minecraft:sneak_time":162,"minecraft:jump":48,"minecraft:leave_game":2,"minecraft:time_since_death":3711,"minecraft:total_world_time":25899,"minecraft:fall_one_cm":2576},"minecraft:killed":{"born_in_chaos_v1:corpse_fly":1},"minecraft:crafted":{"minecraft:crafting_table":1,"minecraft:spruce_planks":36,"minecraft:stick":8,"minecraft:wooden_pickaxe":1,"minecraft:stone_pickaxe":1,"minecraft:wooden_axe":1,"minecraft:torch":4,"minecraft:stone_axe":1},"minecraft:used":{"minecraft:stone_pickaxe":67,"minecraft:wooden_pickaxe":39,"minecraft:stone_axe":6,"minecraft:dirt":1,"minecraft:cobblestone":1,"minecraft:crafting_table":1,"minecraft:granite":2}},"DataVersion":3465}